{
 "type": "wiki",
 "title": "ROOT",
 "url": "/wiki/index",
 "updated": "2023-01-21 23:11:16 +0900",
 "resource": "A7/35E2F5-981B-4E21-AE4D-34850826262D",
 "children": [
  "abbr",
  "algorithm",
  "archive-org-games",
  "bell-labs",
  "better-work",
  "big-numbers",
  "blog",
  "clipping",
  "color-model",
  "crypto",
  "database",
  "diary",
  "exchange-rate",
  "gnu-project",
  "hack",
  "how-to",
  "integer",
  "jargon",
  "java/gc",
  "junit5-nested",
  "kafka",
  "kotlin",
  "language",
  "links",
  "locking",
  "mac",
  "mac-address",
  "mac-tex",
  "math",
  "memo",
  "oauth",
  "oop-quotes",
  "pattern",
  "pension",
  "people",
  "problem",
  "programming",
  "regex",
  "responsibility-driven-design",
  "review",
  "rfc",
  "saga",
  "semantic-versioning",
  "semiconductor-dict",
  "software-engineering",
  "spring",
  "study",
  "summary",
  "three-dots-in-menu",
  "til",
  "timeline",
  "tools",
  "two-type-error",
  "uml",
  "vim",
  "web-browser-vim",
  "what",
  "why"
 ]
}