{"fileName":"diary","collection":{"diary":{"type":"wiki","title":"Diary","parent":"index","url":"/wiki/diary","updated":"2019-08-13 13:50:57 +0900","children":["book-log-2019","book-log-2020","memo-2019","memo-2020","memo-2021"]},"memo-2020":{"type":"wiki","title":"2020년 메모","summary":"","parent":"diary","url":"/wiki/memo-2020","updated":"2021-01-10 13:29:30 +0900","children":[]},"memo-2021":{"type":"wiki","title":"2021년 메모","summary":"","parent":"diary","url":"/wiki/memo-2021","updated":"2021-01-25 22:37:01 +0900","children":[]}}}